entitytocodepy/Polynomials.cpython-312-darwin.so
entitytocodepy/__init__.py
entitytocodepy/main.py
entitytocodepy/mathetc.py
entitytocodepy_official-0.1.1.dist-info/METADATA
entitytocodepy_official-0.1.1.dist-info/WHEEL
entitytocodepy_official-0.1.1.dist-info/licenses/LICENCE
entitytocodepy_official-0.1.1.dist-info/RECORD
