Metadata-Version: 2.1
Name: entitytocodepy_official
Version: 0.1.1
Summary: Formula Package for Mathmatical/Physics/Chemistry/economical/(+) calulations
Project-URL: Homepage, https://github.com/BSW-G-D-iph6/Entity-To-Code-Py
Project-URL: Issues, https://github.com/BSW-G-D-iph6/Entity-To-Code-Py/issues
Author-email: Gavin Simpson <gdsimpson3@gmx.com>
License-File: LICENCE
Classifier: License :: OSI Approved :: MIT License
Classifier: Operating System :: OS Independent
Classifier: Programming Language :: Python :: 3
Requires-Python: ~=3.12
